<?xml version="1.0" encoding="UTF-8" standalone="yes"?>
<inkml:ink xmlns:inkml="http://www.w3.org/2003/InkML"><inkml:definitions><inkml:context xml:id="ctx0"><inkml:inkSource xml:id="inkSrc0"><inkml:traceFormat><inkml:channel name="X" type="integer" min="-2.14748E9" max="2.14748E9" units="cm"/><inkml:channel name="Y" type="integer" min="-2.14748E9" max="2.14748E9" units="cm"/><inkml:channel name="F" type="integer" max="32767" units="dev"/></inkml:traceFormat><inkml:channelProperties><inkml:channelProperty channel="X" name="resolution" value="1000" units="1/cm"/><inkml:channelProperty channel="Y" name="resolution" value="1000" units="1/cm"/><inkml:channelProperty channel="F" name="resolution" value="0" units="1/dev"/></inkml:channelProperties></inkml:inkSource><inkml:timestamp xml:id="ts0" timeString="2024-11-14T09:50:57.355"/></inkml:context><inkml:brush xml:id="br0"><inkml:brushProperty name="width" value="0.035" units="cm"/><inkml:brushProperty name="height" value="0.035" units="cm"/><inkml:brushProperty name="color" value="#E71224"/></inkml:brush></inkml:definitions><inkml:trace contextRef="#ctx0" brushRef="#br0">414 556 24575,'183'27'0,"-34"-7"0,-93-14 0,1-2 0,92-6 0,-43 0 0,157 4 0,268-4 0,-294-22 0,-134 24 0,-67 2 0,1-2 0,-1-1 0,58-11 0,165-45 0,-90 32 0,-115 20 0,77-18 0,-127 22 0,-1 0 0,1 0 0,-1 0 0,1 0 0,-1-1 0,0 0 0,1 1 0,-1-1 0,0 0 0,0-1 0,0 1 0,0-1 0,-1 1 0,1-1 0,-1 0 0,1 0 0,-1 0 0,0 0 0,0 0 0,2-7 0,0-1 0,-1 0 0,-1 0 0,0 0 0,-1 0 0,0-18 0,0 18 0,-2 8 0,1-1 0,-1 1 0,0-1 0,0 1 0,-1 0 0,1 0 0,0-1 0,-1 1 0,0 0 0,0 0 0,0 1 0,0-1 0,0 0 0,-1 1 0,1-1 0,-1 1 0,0 0 0,1 0 0,-1 0 0,0 0 0,-5-2 0,-9-6 0,-2 1 0,-22-9 0,-302-96 0,303 105 0,-1 1 0,-76-3 0,41 5 0,-17-1 0,-44-6 0,-78-13 0,-1 9 0,-236 12 0,337 13 0,-131 27 0,145-18 0,0-4 0,-106 0 0,150-13 0,-1 2 0,1 2 0,-69 15 0,109-16 0,1 1 0,-1 1 0,1 1 0,0 0 0,0 1 0,1 1 0,0 0 0,0 1 0,-20 17 0,30-17 0,0-1 0,1 1 0,0 0 0,0 0 0,1 0 0,0 0 0,1 1 0,0-1 0,0 1 0,1 12 0,-4 5 0,5-23 0,0-1 0,0 1 0,0 0 0,0-1 0,0 1 0,1 0 0,-1-1 0,1 1 0,0 0 0,0-1 0,0 1 0,1-1 0,-1 0 0,1 1 0,0-1 0,0 0 0,0 0 0,0 0 0,1 0 0,-1-1 0,1 1 0,0 0 0,-1-1 0,1 0 0,0 0 0,0 0 0,1 0 0,6 3 0,10 4 0,0-1 0,1 0 0,39 7 0,-27-6 0,23 5 0,-29-8 0,-1 1 0,32 14 0,20 3-1365,-72-23-5461</inkml:trace></inkml:ink>